{
	"animations": [
		{
			"offsets": [
				0,
				0
			],
			"loop": false,
			"anim": "idle",
			"fps": 24,
			"name": "Dad idle dance",
			"indices": []
		},
		{
			"loop": false,
			"offsets": [
				0,
				9
			],
			"anim": "singLEFT",
			"fps": 24,
			"name": "Dad Sing Note LEFT",
			"indices": []
		},
		{
			"loop": false,
			"offsets": [
				42,
				-39
			],
			"anim": "singDOWN",
			"fps": 24,
			"name": "Dad Sing Note DOWN",
			"indices": []
		},
		{
			"loop": false,
			"offsets": [
				0,
				77
			],
			"anim": "singUP",
			"fps": 24,
			"name": "Dad Sing Note UP",
			"indices": []
		},
		{
			"loop": false,
			"offsets": [
				0,
				18
			],
			"anim": "singRIGHT",
			"fps": 24,
			"name": "Dad Sing Note RIGHT",
			"indices": []
		}
	],
	"no_antialiasing": false,
	"image": "characters/waffletrap2",
	"position": [
		300,
		0
	],
	"healthicon": "waffle",
	"flip_x": true,
	"healthbar_colors": [
		100,
		100,
		60
	],
	"camera_position": [
		-100,
		30
	],
	"sing_duration": 6.1,
	"scale": 1
}